redvert/__init__.py
redvert/main.py
RedVert-1.5.7.dist-info/METADATA
RedVert-1.5.7.dist-info/WHEEL
RedVert-1.5.7.dist-info/entry_points.txt
RedVert-1.5.7.dist-info/top_level.txt
RedVert-1.5.7.dist-info/RECORD
