Metadata-Version: 2.1
Name: RedVert
Version: 1.5.7
